selenium_uploader_account/__init__.py
selenium_uploader_account/selenium_uploader_account.py
selenium_uploader_account-0.2.3.dist-info/METADATA
selenium_uploader_account-0.2.3.dist-info/WHEEL
selenium_uploader_account-0.2.3.dist-info/top_level.txt
selenium_uploader_account-0.2.3.dist-info/RECORD
