Metadata-Version: 2.1
Name: selenium_uploader_account
Version: 0.2.3
Summary: selenium_uploader_account
Home-page: https://github.com/kkristof200/selenium_uploader_account
Author: Kristof
Classifier: Programming Language :: Python :: 3
Classifier: License :: OSI Approved :: MIT License
Classifier: Operating System :: OS Independent
Requires-Python: >=3.5
